{
"type": "FeatureCollection",
"name": "geo_23_短期入所療養介護（介護医療院）",
"crs": { "type": "name", "properties": { "name": "urn:ogc:def:crs:OGC:1.3:CRS84" } },
"features": [
{ "type": "Feature", "properties": { "内容": "医療法人親和会富田病院　介護医療院【短期入所療養介護（介護医療院）】愛知県名古屋市中川区かの里一丁目３０１番地", "url": "https://www.kaigokensaku.mhlw.go.jp/23/index.php?action_kouhyou_detail_004_kani=true&JigyosyoCd=23B1000016-00&ServiceCd=551&Type=search", "url2": "http://i-shinwakai.jp/" }, "geometry": { "type": "Point", "coordinates": [ 136.8148918, 35.133548600000097 ] } },
{ "type": "Feature", "properties": { "内容": "介護医療院名南ふれあい病院【短期入所療養介護（介護医療院）】愛知県名古屋市南区豊田五丁目15番18号", "url": "https://www.kaigokensaku.mhlw.go.jp/23/index.php?action_kouhyou_detail_004_kani=true&JigyosyoCd=23B1200012-00&ServiceCd=551&Type=search", "url2": "http://www.meinan.or.jp" }, "geometry": { "type": "Point", "coordinates": [ 136.915127500000011, 35.1014516 ] } },
{ "type": "Feature", "properties": { "内容": "医療法人　博報会　岡崎東病院　介護医療院【短期入所療養介護（介護医療院）】愛知県岡崎市洞町字向山16番地2", "url": "https://www.kaigokensaku.mhlw.go.jp/23/index.php?action_kouhyou_detail_004_kani=true&JigyosyoCd=23B2100013-00&ServiceCd=551&Type=search", "url2": "https://okazakihigashi-hp.jp/" }, "geometry": { "type": "Point", "coordinates": [ 137.199249, 34.9462325 ] } },
{ "type": "Feature", "properties": { "内容": "水野介護医療院【短期入所療養介護（介護医療院）】愛知県瀬戸市小田妻町1丁目190番地の2", "url": "https://www.kaigokensaku.mhlw.go.jp/23/index.php?action_kouhyou_detail_004_kani=true&JigyosyoCd=23B2300019-00&ServiceCd=551&Type=search", "url2": "http://kouseikai2231.jp/" }, "geometry": { "type": "Point", "coordinates": [ 137.07533620000001, 35.2417286 ] } },
{ "type": "Feature", "properties": { "内容": "足助病院　介護医療院【短期入所療養介護（介護医療院）】愛知県豊田市岩神町仲田２０番地", "url": "https://www.kaigokensaku.mhlw.go.jp/23/index.php?action_kouhyou_detail_004_kani=true&JigyosyoCd=23B3000014-00&ServiceCd=551&Type=search", "url2": "https://asukehp.or.jp/" }, "geometry": { "type": "Point", "coordinates": [ 137.305657599999989, 35.1303259 ] } },
{ "type": "Feature", "properties": { "内容": "医療法人真清会　新川病院介護医療院【短期入所療養介護（介護医療院）】愛知県清須市土器野２６７番地", "url": "https://www.kaigokensaku.mhlw.go.jp/23/index.php?action_kouhyou_detail_004_kani=true&JigyosyoCd=23B7300014-00&ServiceCd=551&Type=search", "url2": "https://shinkawa-hospital.com/" }, "geometry": { "type": "Point", "coordinates": [ 136.8541442, 35.1938105 ] } },
{ "type": "Feature", "properties": { "内容": "済衆館介護医療院【短期入所療養介護（介護医療院）】愛知県北名古屋市鹿田西村前111番地", "url": "https://www.kaigokensaku.mhlw.go.jp/23/index.php?action_kouhyou_detail_004_kani=true&JigyosyoCd=23B7400012-00&ServiceCd=551&Type=search", "url2": "https://saishukan.com" }, "geometry": { "type": "Point", "coordinates": [ 136.8772697, 35.2423717 ] } }
]
}
